deepctx/__init__.py
deepctx/hardware.py
deepctx/lazy.py
deepctx/integration/__init__.py
deepctx/integration/slurm/__init__.py
deepctx/integration/tensorflow/__init__.py
deepctx/integration/tensorflow/devices.py
deepctx/integration/tensorflow/strategy.py
deepctx/integration/tensorflow/keras/__init__.py
deepctx/integration/tensorflow/keras/callbacks.py
deepctx/scripting/__init__.py
deepctx/scripting/context.py
deepctx/scripting/module/__init__.py
deepctx/scripting/module/rng_module.py
deepctx/scripting/module/train_module.py
deepctx/scripting/module/wandb_module.py
deepctx/scripting/module/tensorflow_module/__init__.py
deepctx/scripting/module/tensorflow_module/callbacks.py
deepctx/utils/__init__.py
deepctx/utils/lazyloading.py
deepctx-0.0.26.dist-info/LICENSE
deepctx-0.0.26.dist-info/METADATA
deepctx-0.0.26.dist-info/WHEEL
deepctx-0.0.26.dist-info/top_level.txt
deepctx-0.0.26.dist-info/RECORD
