Metadata-Version: 2.1
Name: deepctx
Version: 0.0.26
Summary: A light-weight library that simplifies the scripting process for deep-learning related tasks.
Author-email: David Ludwig <davidludwigii@gmail.com>
License: MIT License
Project-URL: Homepage, https://github.com/DLii-Research/deepctx
Project-URL: Bug Tracker, https://github.com/DLii-Research/deepctx/issues
Classifier: Programming Language :: Python :: 3
Classifier: License :: OSI Approved :: MIT License
Classifier: Operating System :: OS Independent
Requires-Python: >=3.8
License-File: LICENSE
Requires-Dist: wandb >=0.15.10
